email_utilities/__init__.py
email_utilities/email_conversion.py
email_utilities/email_insights.py
email_utilities-1.0.5.dist-info/LICENSE
email_utilities-1.0.5.dist-info/METADATA
email_utilities-1.0.5.dist-info/WHEEL
email_utilities-1.0.5.dist-info/top_level.txt
email_utilities-1.0.5.dist-info/RECORD
